{
  "name": "[IQB7] Whizkid05",
  "demonlistRank": 17,
  "demonlistScore": 4936.510279671396,
  "demonlistStats": {
    "main": 36,
    "extended": 0,
    "legacy": 0
  },
  "hardestDemon": "Anathema",
  "demonsCompleted": [
    "ATOMIC CANNON Mk II",
    "Anathema",
    "BEELINE",
    "BPATA MPAKA",
    "Checked Steam",
    "Codependence",
    "Coral Cave",
    "Crystal Crusher",
    "Delta",
    "Edge of Destiny",
    "Eyes in the Water",
    "Frost Spirit",
    "Guideless Goobering",
    "Hard Machine",
    "Horros",
    "Instinct",
    "Launchpad Labyrinth",
    "Lotus Flower",
    "Menace",
    "NEUTRA",
    "Rigel",
    "SAND SAILOR",
    "SARYYX NEVER CLEAR",
    "Saul Goodman",
    "Scrubbabingo force",
    "Sides Of My Mind",
    "Solar Flare",
    "Sonic Wave Infinity",
    "Starlit Stroll",
    "Swing Swing",
    "Tenkai",
    "The Lightning Rod",
    "UNKNOWN",
    "VOID",
    "We Are Not The Same",
    "walter white"
  ],
  "demonsVerified": [
    "Anathema",
    "Checked Steam",
    "Menace",
    "Swing Swing",
    "VOID"
  ],
  "records": []
}