{
  "name": "[YAHO] Seturan",
  "demonlistRank": 42,
  "demonlistScore": 3193.778552227458,
  "demonlistStats": {
    "main": 20,
    "extended": 0,
    "legacy": 0
  },
  "hardestDemon": "Silent clubstep",
  "demonsCompleted": [
    "Abyss of Darkness",
    "Cognition",
    "Deadlier Clubstep",
    "Eyes in the Water",
    "Hard Machine",
    "Launchpad Labyrinth",
    "Lucid Nightmares",
    "NETWORK",
    "Promethean",
    "RUTHLESS",
    "Sakupen Circles",
    "Saul Goodman",
    "Silent clubstep",
    "The Golden",
    "The Plunge",
    "Zodiac",
    "arcturus",
    "qoUEO",
    "shimmer",
    "walter white"
  ],
  "demonsVerified": [],
  "records": []
}