{
  "name": "Axinity",
  "demonlistRank": 43,
  "demonlistScore": 2890.995925349991,
  "demonlistStats": {
    "main": 16,
    "extended": 0,
    "legacy": 0
  },
  "hardestDemon": "Acheron",
  "demonsCompleted": [
    "Acheron",
    "Cognition",
    "Crimson Planet",
    "Firework",
    "Fragile",
    "Kenos",
    "Keres",
    "Mayhem",
    "Midnight",
    "Oblivion",
    "Sakupen Circles",
    "Solar Flare",
    "Sonic Wave Infinity",
    "The Golden",
    "The Hallucination",
    "arcturus"
  ],
  "demonsVerified": [],
  "records": []
}